[
  {
    "business_name": "Almanza Roofing & Gutters",
    "street_address": "4603 S Keating Ave",
    "city": "Chicago",
    "state": "IL",
    "postal_code": "60632-4822",
    "phone": "(773) 918-9277",
    "email": "",
    "website": "",
    "entity_type": "",
    "business_started": "",
    "incorporated_date": "",
    "principal_contact": "",
    "business_categories": "Roofing Contractors; Insulation Contractors; Construction; Flat Roofing Contractors",
    "rating": "A+",
    "bbb_member": "true",
    "bbb_accredited": "false",
    "source_url": "https://www.bbb.org/us/il/chicago/profile/roofing-contractors/almanza-roofing-gutters-0654-1000013469"
  },
  {
    "business_name": "Standard Exteriors Co.",
    "street_address": "980 N Michigan Ave Ste 1090 PMB 887437",
    "city": "Chicago",
    "state": "IL",
    "postal_code": "60611-4521",
    "phone": "(312) 564-5355",
    "email": "",
    "website": "",
    "entity_type": "",
    "business_started": "",
    "incorporated_date": "",
    "principal_contact": "",
    "business_categories": "Roofing Contractors; Siding Contractors; Metal Roofing Contractors; Commercial Roofing",
    "rating": "A-",
    "bbb_member": "true",
    "bbb_accredited": "true",
    "source_url": "https://www.bbb.org/us/il/chicago/profile/roofing-contractors/standard-exteriors-co-0654-1000128758"
  },
  {
    "business_name": "AFR Roofing & Construction PLLC.",
    "street_address": "1965 W Pershing Rd",
    "city": "Chicago",
    "state": "IL",
    "postal_code": "60609-2315",
    "phone": "(312) 877-7549",
    "email": "",
    "website": "",
    "entity_type": "",
    "business_started": "",
    "incorporated_date": "",
    "principal_contact": "",
    "business_categories": "Roofing Contractors; Siding Contractors; Commercial Roofing; Skylights",
    "rating": "A+",
    "bbb_member": "true",
    "bbb_accredited": "false",
    "source_url": "https://www.bbb.org/us/il/chicago/profile/roofing-contractors/afr-roofing-construction-pllc-0654-1000095668"
  },
  {
    "business_name": "JJA Roofing & Contracting",
    "street_address": "1965 W Pershing Rd",
    "city": "Chicago",
    "state": "IL",
    "postal_code": "60609-2315",
    "phone": "(708) 971-6135",
    "email": "",
    "website": "",
    "entity_type": "",
    "business_started": "",
    "incorporated_date": "",
    "principal_contact": "",
    "business_categories": "Roofing Contractors; Siding Contractors; Gutter Contractors",
    "rating": "A+",
    "bbb_member": "true",
    "bbb_accredited": "true",
    "source_url": "https://www.bbb.org/us/il/chicago/profile/roofing-contractors/jja-roofing-contracting-0654-90026251"
  },
  {
    "business_name": "Allendorfer Roofing Co., Ltd.",
    "street_address": "4030 N Nashville Ave",
    "city": "Chicago",
    "state": "IL",
    "postal_code": "60634-1427",
    "phone": "(773) 463-7808",
    "email": "",
    "website": "",
    "entity_type": "",
    "business_started": "",
    "incorporated_date": "",
    "principal_contact": "",
    "business_categories": "Roofing Contractors; Siding Contractors; Mason Contractors; Gutters",
    "rating": "A+",
    "bbb_member": "true",
    "bbb_accredited": "false",
    "source_url": "https://www.bbb.org/us/il/chicago/profile/roofing-contractors/allendorfer-roofing-co-ltd-0654-12008019"
  },
  {
    "business_name": "Nicholas Flat Roofing & Paving",
    "street_address": "159 N Sangamon St",
    "city": "Chicago",
    "state": "IL",
    "postal_code": "60607-2201",
    "phone": "(773) 682-4950",
    "email": "",
    "website": "",
    "entity_type": "",
    "business_started": "",
    "incorporated_date": "",
    "principal_contact": "",
    "business_categories": "Roofing Contractors; Paving Contractors; Asphalt; Commercial Roofing",
    "rating": "A+",
    "bbb_member": "true",
    "bbb_accredited": "true",
    "source_url": "https://www.bbb.org/us/il/chicago/profile/roofing-contractors/nicholas-flat-roofing-paving-0654-1000098640"
  },
  {
    "business_name": "Chicago Prestige Roofing LLC",
    "street_address": "2038 S Halsted St",
    "city": "Chicago",
    "state": "IL",
    "postal_code": "60608-3449",
    "phone": "(312) 632-4603",
    "email": "",
    "website": "",
    "entity_type": "",
    "business_started": "",
    "incorporated_date": "",
    "principal_contact": "",
    "business_categories": "Roofing Contractors; Commercial Roofing; Flat Roofing Contractors; Roof Inspection",
    "rating": "A+",
    "bbb_member": "true",
    "bbb_accredited": "true",
    "source_url": "https://www.bbb.org/us/il/chicago/profile/roofing-contractors/chicago-prestige-roofing-llc-0654-1000112427"
  },
  {
    "business_name": "Your Mid America Exteriors",
    "street_address": "27 N Wacker Dr suite 244",
    "city": "Chicago",
    "state": "IL",
    "postal_code": "60606-2800",
    "phone": "(773) 669-6542",
    "email": "",
    "website": "",
    "entity_type": "",
    "business_started": "",
    "incorporated_date": "",
    "principal_contact": "",
    "business_categories": "Siding Contractors; Roofing Contractors; Gutters; Soffit and Fascia",
    "rating": "A+",
    "bbb_member": "true",
    "bbb_accredited": "true",
    "source_url": "https://www.bbb.org/us/il/chicago/profile/siding-contractors/your-mid-america-exteriors-0654-90016001"
  },
  {
    "business_name": "Nombach Roofing & Tuckpointing",
    "street_address": "819 N MILWAUKEE AVE, UNIT 1",
    "city": "Chicago",
    "state": "IL",
    "postal_code": "60642",
    "phone": "(708) 388-1090",
    "email": "",
    "website": "",
    "entity_type": "",
    "business_started": "",
    "incorporated_date": "",
    "principal_contact": "",
    "business_categories": "Roofing Contractors; Concrete Contractors; Mason Contractors; Gutters",
    "rating": "A+",
    "bbb_member": "true",
    "bbb_accredited": "true",
    "source_url": "https://www.bbb.org/us/il/chicago/profile/roofing-contractors/nombach-roofing-tuckpointing-0654-10031"
  },
  {
    "business_name": "Active Roofing Company, Inc.",
    "street_address": "2100 W 32nd St",
    "city": "Chicago",
    "state": "IL",
    "postal_code": "60608-6030",
    "phone": "(708) 430-8080",
    "email": "",
    "website": "",
    "entity_type": "",
    "business_started": "",
    "incorporated_date": "",
    "principal_contact": "",
    "business_categories": "Commercial Roofing; Roofing Contractors; Metal Roofing Contractors; Flat Roofing Contractors",
    "rating": "A+",
    "bbb_member": "true",
    "bbb_accredited": "false",
    "source_url": "https://www.bbb.org/us/il/chicago/profile/commercial-roofing/active-roofing-company-inc-0654-88386303"
  },
  {
    "business_name": "Top Level Roofing PLLC",
    "street_address": "332 S Michigan Ave Ste 121",
    "city": "Chicago",
    "state": "IL",
    "postal_code": "60604-4302",
    "phone": "(312) 661-2400",
    "email": "",
    "website": "",
    "entity_type": "",
    "business_started": "",
    "incorporated_date": "",
    "principal_contact": "",
    "business_categories": "Roofing Contractors; Siding Contractors; Windows; Window Installation",
    "rating": "A ",
    "bbb_member": "true",
    "bbb_accredited": "true",
    "source_url": "https://www.bbb.org/us/il/chicago/profile/roofing-contractors/top-level-roofing-pllc-0654-1000108238"
  },
  {
    "business_name": "TTLC Inc. - Roofing, Siding & Gutters",
    "street_address": "9 N Wabash Ave",
    "city": "Chicago",
    "state": "IL",
    "postal_code": "60602-4715",
    "phone": "(815) 569-0234",
    "email": "",
    "website": "",
    "entity_type": "",
    "business_started": "",
    "incorporated_date": "",
    "principal_contact": "",
    "business_categories": "Roofing Contractors; Siding Contractors; Gutters; Window Installation",
    "rating": "A+",
    "bbb_member": "true",
    "bbb_accredited": "true",
    "source_url": "https://www.bbb.org/us/il/plainfield/profile/roofing-contractors/ttlc-inc-roofing-siding-gutters-0654-1000028400"
  },
  {
    "business_name": "Andrew`s Roof and Gutter Maintenance",
    "street_address": "2232 S Hamlin Ave",
    "city": "Chicago",
    "state": "IL",
    "postal_code": "60623-3020",
    "phone": "(773) 403-2145",
    "email": "",
    "website": "",
    "entity_type": "",
    "business_started": "",
    "incorporated_date": "",
    "principal_contact": "",
    "business_categories": "Roofing Contractors; Siding Contractors; Gutters; Chimney Repair",
    "rating": "A+",
    "bbb_member": "true",
    "bbb_accredited": "true",
    "source_url": "https://www.bbb.org/us/il/chicago/profile/roofing-contractors/andrew%60s-roof-and-gutter-maintenance-0654-1000101766"
  },
  {
    "business_name": "Chicago Star Roofing",
    "street_address": "939 W North Ave Ste 750",
    "city": "Chicago",
    "state": "IL",
    "postal_code": "60642-7142",
    "phone": "(708) 925-8895",
    "email": "",
    "website": "",
    "entity_type": "",
    "business_started": "",
    "incorporated_date": "",
    "principal_contact": "",
    "business_categories": "Roofing Contractors; Siding Contractors; Gutters; Metal Roofing Contractors",
    "rating": "A+",
    "bbb_member": "true",
    "bbb_accredited": "false",
    "source_url": "https://www.bbb.org/us/il/chicago/profile/roofing-contractors/chicago-star-roofing-0654-90020103"
  },
  {
    "business_name": "Nicholas Flat Roofing & Paving",
    "street_address": "1727 N. Wester Ave. Unit C1",
    "city": "Chicago",
    "state": "IL",
    "postal_code": "60647",
    "phone": "(773) 682-4950",
    "email": "",
    "website": "",
    "entity_type": "",
    "business_started": "",
    "incorporated_date": "",
    "principal_contact": "",
    "business_categories": "Roofing Contractors; Paving Contractors; Asphalt; Commercial Roofing",
    "rating": "A+",
    "bbb_member": "true",
    "bbb_accredited": "true",
    "source_url": "https://www.bbb.org/us/il/chicago/profile/roofing-contractors/nicholas-flat-roofing-paving-0654-1000098640"
  },
  {
    "business_name": "Chicago Roofing Systems",
    "street_address": "3810 S Emerald Ave",
    "city": "Chicago",
    "state": "IL",
    "postal_code": "60609-1601",
    "phone": "(847) 812-0004",
    "email": "",
    "website": "",
    "entity_type": "",
    "business_started": "",
    "incorporated_date": "",
    "principal_contact": "",
    "business_categories": "Roofing Contractors; Gutters; Metal Roofing Contractors; Commercial Roofing",
    "rating": "A-",
    "bbb_member": "true",
    "bbb_accredited": "true",
    "source_url": "https://www.bbb.org/us/il/chicago/profile/roofing-contractors/chicago-roofing-systems-0654-1000127522"
  },
  {
    "business_name": "Matthews Roofing Company, Inc.",
    "street_address": "3737 W. North Ave.",
    "city": "Chicago",
    "state": "IL",
    "postal_code": "60647-4760",
    "phone": "(773) 276-4100",
    "email": "",
    "website": "",
    "entity_type": "",
    "business_started": "",
    "incorporated_date": "",
    "principal_contact": "",
    "business_categories": "Roofing Contractors; Gutters; Asphalt; Commercial Roofing",
    "rating": "A+",
    "bbb_member": "true",
    "bbb_accredited": "true",
    "source_url": "https://www.bbb.org/us/il/chicago/profile/roofing-contractors/matthews-roofing-company-inc-0654-4986"
  },
  {
    "business_name": "J & P Exteriors 1 Inc.",
    "street_address": "1822 N Saint Louis Ave",
    "city": "Chicago",
    "state": "IL",
    "postal_code": "60647-4825",
    "phone": "(773) 574-7310",
    "email": "",
    "website": "",
    "entity_type": "",
    "business_started": "",
    "incorporated_date": "",
    "principal_contact": "",
    "business_categories": "Roofing Contractors; Painting Contractors; Siding Contractors; Metal Roofing Contractors",
    "rating": "A+",
    "bbb_member": "true",
    "bbb_accredited": "true",
    "source_url": "https://www.bbb.org/us/il/chicago/profile/roofing-contractors/j-p-exteriors-1-inc-0654-1000048262"
  },
  {
    "business_name": "Tri-Star Roofing",
    "street_address": "1229 N Monticello Ave",
    "city": "Chicago",
    "state": "IL",
    "postal_code": "60651-2227",
    "phone": "(773) 395-2608",
    "email": "",
    "website": "",
    "entity_type": "",
    "business_started": "",
    "incorporated_date": "",
    "principal_contact": "",
    "business_categories": "Roofing Contractors; Gutters; Roof Cleaning",
    "rating": "A+",
    "bbb_member": "true",
    "bbb_accredited": "true",
    "source_url": "https://www.bbb.org/us/il/chicago/profile/roofing-contractors/tri-star-roofing-0654-75000321"
  },
  {
    "business_name": "Star Roofing & Siding Co., Inc.",
    "street_address": "1930 N Springfield Ave",
    "city": "Chicago",
    "state": "IL",
    "postal_code": "60647-3420",
    "phone": "(773) 342-6719",
    "email": "",
    "website": "",
    "entity_type": "",
    "business_started": "",
    "incorporated_date": "",
    "principal_contact": "",
    "business_categories": "Roofing Contractors; Siding Contractors; Gutter Cleaning; Commercial Roofing",
    "rating": "A+",
    "bbb_member": "true",
    "bbb_accredited": "false",
    "source_url": "https://www.bbb.org/us/il/chicago/profile/roofing-contractors/star-roofing-siding-co-inc-0654-17000212"
  },
  {
    "business_name": "On Guard Roofing PLLC",
    "street_address": "4546 S California Ave",
    "city": "Chicago",
    "state": "IL",
    "postal_code": "60632-1935",
    "phone": "(773) 715-8755",
    "email": "",
    "website": "",
    "entity_type": "",
    "business_started": "",
    "incorporated_date": "",
    "principal_contact": "",
    "business_categories": "Roofing Contractors; Siding Contractors; Gutters; Flat Roofing Contractors",
    "rating": "A+",
    "bbb_member": "true",
    "bbb_accredited": "false",
    "source_url": "https://www.bbb.org/us/il/chicago/profile/roofing-contractors/on-guard-roofing-pllc-0654-1000097481"
  },
  {
    "business_name": "Expert Super Seal Roofing & Tuckpointing",
    "street_address": "1909 W Diversey Pkwy",
    "city": "Chicago",
    "state": "IL",
    "postal_code": "60614-9417",
    "phone": "(773) 993-5668",
    "email": "",
    "website": "",
    "entity_type": "",
    "business_started": "",
    "incorporated_date": "",
    "principal_contact": "",
    "business_categories": "Roofing Contractors; Mason Contractors; Metal Roofing Contractors; Waterproofing Contractors",
    "rating": "A+",
    "bbb_member": "true",
    "bbb_accredited": "true",
    "source_url": "https://www.bbb.org/us/il/chicago/profile/roofing-contractors/expert-super-seal-roofing-tuckpointing-0654-90019401"
  },
  {
    "business_name": "Luna's Roofing Svc",
    "street_address": "5117 W Monroe St",
    "city": "Chicago",
    "state": "IL",
    "postal_code": "60644-5596",
    "phone": "(773) 418-2040",
    "email": "",
    "website": "",
    "entity_type": "",
    "business_started": "",
    "incorporated_date": "",
    "principal_contact": "",
    "business_categories": "Roofing Contractors; Siding Contractors; Gutters; Tuckpointing",
    "rating": "A+",
    "bbb_member": "true",
    "bbb_accredited": "false",
    "source_url": "https://www.bbb.org/us/il/chicago/profile/roofing-contractors/lunas-roofing-svc-0654-88553534"
  },
  {
    "business_name": "Crown Roofing and Construction Incorporated",
    "street_address": "4624 S California Ave",
    "city": "Chicago",
    "state": "IL",
    "postal_code": "60632-1909",
    "phone": "(773) 968-5220",
    "email": "",
    "website": "",
    "entity_type": "",
    "business_started": "",
    "incorporated_date": "",
    "principal_contact": "",
    "business_categories": "Roofing Contractors; Siding Contractors; Commercial Roofing; Flat Roofing Contractors",
    "rating": "A+",
    "bbb_member": "true",
    "bbb_accredited": "true",
    "source_url": "https://www.bbb.org/us/il/chicago/profile/roofing-contractors/crown-roofing-and-construction-incorporated-0654-88347548"
  },
  {
    "business_name": "Second City Roofing & Exteriors",
    "street_address": "3006 W Diversey Ave",
    "city": "Chicago",
    "state": "IL",
    "postal_code": "60647-1726",
    "phone": "(773) 384-6300",
    "email": "",
    "website": "",
    "entity_type": "",
    "business_started": "",
    "incorporated_date": "",
    "principal_contact": "",
    "business_categories": "Roofing Contractors; Siding Contractors; Mason Contractors; Patios and Decks",
    "rating": "A+",
    "bbb_member": "true",
    "bbb_accredited": "true",
    "source_url": "https://www.bbb.org/us/il/chicago/profile/roofing-contractors/second-city-roofing-exteriors-0654-30000158"
  },
  {
    "business_name": "Perez Roofing Inc.",
    "street_address": "4926 S Damen Ave",
    "city": "Chicago",
    "state": "IL",
    "postal_code": "60609-4714",
    "phone": "(773) 491-2968",
    "email": "",
    "website": "",
    "entity_type": "",
    "business_started": "",
    "incorporated_date": "",
    "principal_contact": "",
    "business_categories": "Roofing Contractors; Mason Contractors; Commercial Roofing; Flat Roofing Contractors",
    "rating": "A+",
    "bbb_member": "true",
    "bbb_accredited": "false",
    "source_url": "https://www.bbb.org/us/il/chicago/profile/roofing-contractors/perez-roofing-inc-0654-1000043471"
  },
  {
    "business_name": "Cobblestone Exteriors LLC",
    "street_address": "3062 N Clybourn Ave",
    "city": "Chicago",
    "state": "IL",
    "postal_code": "60618",
    "phone": "(773) 888-6880",
    "email": "",
    "website": "",
    "entity_type": "",
    "business_started": "",
    "incorporated_date": "",
    "principal_contact": "",
    "business_categories": "General Contractor; Roofing Contractors; Fence Contractors; Siding Contractors",
    "rating": "A-",
    "bbb_member": "true",
    "bbb_accredited": "true",
    "source_url": "https://www.bbb.org/us/il/chicago/profile/general-contractor/cobblestone-exteriors-llc-0654-1000127403"
  },
  {
    "business_name": "Gutter Wilson PLLC-Siding-Roofing",
    "street_address": "631 N Lotus Ave",
    "city": "Chicago",
    "state": "IL",
    "postal_code": "60644-1514",
    "phone": "(312) 774-8837",
    "email": "",
    "website": "",
    "entity_type": "",
    "business_started": "",
    "incorporated_date": "",
    "principal_contact": "",
    "business_categories": "Roofing Contractors; Siding Contractors; Gutters; Gutter Cleaning",
    "rating": "A+",
    "bbb_member": "true",
    "bbb_accredited": "true",
    "source_url": "https://www.bbb.org/us/il/chicago/profile/roofing-contractors/gutter-wilson-pllc-siding-roofing-0654-1000109053"
  },
  {
    "business_name": "Chicago Roofing Assistance Company",
    "street_address": "2923 N Milwaukee Ave Ste 316",
    "city": "Chicago",
    "state": "IL",
    "postal_code": "60618-7892",
    "phone": "(773) 620-0038",
    "email": "",
    "website": "",
    "entity_type": "",
    "business_started": "",
    "incorporated_date": "",
    "principal_contact": "",
    "business_categories": "Roofing Contractors; Metal Roofing Contractors; Commercial Roofing; Flat Roofing Contractors",
    "rating": "A+",
    "bbb_member": "true",
    "bbb_accredited": "false",
    "source_url": "https://www.bbb.org/us/il/chicago/profile/roofing-contractors/chicago-roofing-assistance-company-0654-1000016915"
  },
  {
    "business_name": "Dardon's Exteriors, Inc.",
    "street_address": "PO Box 180231",
    "city": "Chicago",
    "state": "IL",
    "postal_code": "60618-0618",
    "phone": "(773) 447-6423",
    "email": "",
    "website": "",
    "entity_type": "",
    "business_started": "",
    "incorporated_date": "",
    "principal_contact": "",
    "business_categories": "Roofing Contractors; Siding Contractors; Gutters; Metal Roofing Contractors",
    "rating": "A+",
    "bbb_member": "true",
    "bbb_accredited": "true",
    "source_url": "https://www.bbb.org/us/il/chicago/profile/roofing-contractors/dardons-exteriors-inc-0654-67000946"
  },
  {
    "business_name": "SAL Roofing & Restoration",
    "street_address": "5655 S Fairfield Ave",
    "city": "Chicago",
    "state": "IL",
    "postal_code": "60629",
    "phone": "(708) 829-2714",
    "email": "",
    "website": "",
    "entity_type": "",
    "business_started": "",
    "incorporated_date": "",
    "principal_contact": "",
    "business_categories": "Residential Roofing; Roofing Contractors; Siding Contractors; Gutters",
    "rating": "A+",
    "bbb_member": "true",
    "bbb_accredited": "false",
    "source_url": "https://www.bbb.org/us/il/chicago/profile/residential-roofing/sal-roofing-restoration-0654-1000103402"
  },
  {
    "business_name": "Chicago Roof Check & Adjusting Co.",
    "street_address": "4721 S Cicero Ave",
    "city": "Chicago",
    "state": "IL",
    "postal_code": "60632-4807",
    "phone": "(312) 300-4858",
    "email": "",
    "website": "",
    "entity_type": "",
    "business_started": "",
    "incorporated_date": "",
    "principal_contact": "",
    "business_categories": "Public Adjuster; Roofing Contractors; Roofing Consultants; Roof Leak Repair",
    "rating": "A+",
    "bbb_member": "true",
    "bbb_accredited": "false",
    "source_url": "https://www.bbb.org/us/il/chicago/profile/public-adjuster/chicago-roof-check-adjusting-co-0654-88655193"
  },
  {
    "business_name": "J Z Roofing of Chicago, Inc.",
    "street_address": "4341 W Melrose St",
    "city": "Chicago",
    "state": "IL",
    "postal_code": "60641-4548",
    "phone": "(773) 930-4422",
    "email": "",
    "website": "",
    "entity_type": "",
    "business_started": "",
    "incorporated_date": "",
    "principal_contact": "",
    "business_categories": "Roofing Contractors; Siding Contractors; Mason Contractors; Gutters",
    "rating": "A+",
    "bbb_member": "true",
    "bbb_accredited": "true",
    "source_url": "https://www.bbb.org/us/il/chicago/profile/roofing-contractors/j-z-roofing-of-chicago-inc-0654-88378498"
  },
  {
    "business_name": "Advanced Roofing & Masonry, Inc.",
    "street_address": "5359 S Tripp Ave",
    "city": "Chicago",
    "state": "IL",
    "postal_code": "60632-4605",
    "phone": "(773) 574-6830",
    "email": "",
    "website": "",
    "entity_type": "",
    "business_started": "",
    "incorporated_date": "",
    "principal_contact": "",
    "business_categories": "Roofing Contractors; Siding Contractors; Mason Contractors; Gutters",
    "rating": "A+",
    "bbb_member": "true",
    "bbb_accredited": "true",
    "source_url": "https://www.bbb.org/us/il/chicago/profile/roofing-contractors/advanced-roofing-masonry-inc-0654-1000103713"
  },
  {
    "business_name": "Star Roofing & Construction, Inc.",
    "street_address": "3539 N. Milwaukee Ave.",
    "city": "Chicago",
    "state": "IL",
    "postal_code": "60641-3957",
    "phone": "(773) 282-0100",
    "email": "",
    "website": "",
    "entity_type": "",
    "business_started": "",
    "incorporated_date": "",
    "principal_contact": "",
    "business_categories": "Roofing Contractors; General Contractor; Fire and Water Damage Restoration; Water Damage Restoration",
    "rating": "A+",
    "bbb_member": "true",
    "bbb_accredited": "false",
    "source_url": "https://www.bbb.org/us/il/chicago/profile/roofing-contractors/star-roofing-construction-inc-0654-36000084"
  },
  {
    "business_name": "Lindholm Roofing",
    "street_address": "3588 N Milwaukee Ave",
    "city": "Chicago",
    "state": "IL",
    "postal_code": "60641-3959",
    "phone": "(773) 283-7675",
    "email": "",
    "website": "",
    "entity_type": "",
    "business_started": "",
    "incorporated_date": "",
    "principal_contact": "",
    "business_categories": "Roofing Contractors; Siding Contractors; Gutters; Window Installation",
    "rating": "A+",
    "bbb_member": "true",
    "bbb_accredited": "true",
    "source_url": "https://www.bbb.org/us/il/chicago/profile/roofing-contractors/lindholm-roofing-0654-4885"
  },
  {
    "business_name": "A & M Roofing Masonry Co",
    "street_address": "1010 Lake St Ste 200",
    "city": "Oak Park",
    "state": "IL",
    "postal_code": "60301-1132",
    "phone": "(773) 949-5003",
    "email": "",
    "website": "",
    "entity_type": "",
    "business_started": "",
    "incorporated_date": "",
    "principal_contact": "",
    "business_categories": "Roofing Contractors; Siding Contractors; Mason Contractors; Bathroom Remodel",
    "rating": "A ",
    "bbb_member": "true",
    "bbb_accredited": "false",
    "source_url": "https://www.bbb.org/us/il/oak-park/profile/roofing-contractors/a-m-roofing-masonry-co-0654-1000115677"
  },
  {
    "business_name": "Make It Happen Roofing",
    "street_address": "3245 Grove Ave Ste 202",
    "city": "Berwyn",
    "state": "IL",
    "postal_code": "60402-3475",
    "phone": "(708) 416-8098",
    "email": "",
    "website": "",
    "entity_type": "",
    "business_started": "",
    "incorporated_date": "",
    "principal_contact": "",
    "business_categories": "Roofing Contractors; Siding Contractors; Metal Roofing Contractors; Commercial Roofing",
    "rating": "A+",
    "bbb_member": "true",
    "bbb_accredited": "true",
    "source_url": "https://www.bbb.org/us/il/berwyn/profile/roofing-contractors/make-it-happen-roofing-0654-1000012007"
  },
  {
    "business_name": "Pulaski Roofing & Construction Co",
    "street_address": "7301 W 25th St",
    "city": "N Riverside",
    "state": "IL",
    "postal_code": "60546",
    "phone": "(708) 762-1005",
    "email": "",
    "website": "",
    "entity_type": "",
    "business_started": "",
    "incorporated_date": "",
    "principal_contact": "",
    "business_categories": "Roofing Contractors; Metal Roofing Contractors; Commercial Roofing; Flat Roofing Contractors",
    "rating": "A ",
    "bbb_member": "true",
    "bbb_accredited": "false",
    "source_url": "https://www.bbb.org/us/il/n-riverside/profile/roofing-contractors/pulaski-roofing-construction-co-0654-90006920"
  },
  {
    "business_name": "Tans Quality Roofing, Inc.",
    "street_address": "4591 N Elston Ave",
    "city": "Chicago",
    "state": "IL",
    "postal_code": "60630-4214",
    "phone": "(773) 685-0010",
    "email": "",
    "website": "",
    "entity_type": "",
    "business_started": "",
    "incorporated_date": "",
    "principal_contact": "",
    "business_categories": "Roofing Contractors; Gutter Cleaning; Gutter Guards; Roof Leak Repair",
    "rating": "A+",
    "bbb_member": "true",
    "bbb_accredited": "false",
    "source_url": "https://www.bbb.org/us/il/chicago/profile/roofing-contractors/tans-quality-roofing-inc-0654-27006365"
  },
  {
    "business_name": "DM Exteriors, Inc.",
    "street_address": "6641 S Kilbourn Ave",
    "city": "Chicago",
    "state": "IL",
    "postal_code": "60629-5618",
    "phone": "(773) 391-7401",
    "email": "",
    "website": "",
    "entity_type": "",
    "business_started": "",
    "incorporated_date": "",
    "principal_contact": "",
    "business_categories": "Roofing Contractors; Siding Contractors; Gutters; Gutter Guards",
    "rating": "A+",
    "bbb_member": "true",
    "bbb_accredited": "true",
    "source_url": "https://www.bbb.org/us/il/chicago/profile/roofing-contractors/dm-exteriors-inc-0654-90009903"
  },
  {
    "business_name": "PRG Roofing, Inc.",
    "street_address": "3453 N Normandy Ave",
    "city": "Chicago",
    "state": "IL",
    "postal_code": "60634-3718",
    "phone": "(773) 401-5285",
    "email": "",
    "website": "",
    "entity_type": "",
    "business_started": "",
    "incorporated_date": "",
    "principal_contact": "",
    "business_categories": "Roofing Contractors",
    "rating": "A+",
    "bbb_member": "true",
    "bbb_accredited": "true",
    "source_url": "https://www.bbb.org/us/il/chicago/profile/roofing-contractors/prg-roofing-inc-0654-90009297"
  },
  {
    "business_name": "Conrad Roofing of Illinois",
    "street_address": "5122 N Elston Ave",
    "city": "Chicago",
    "state": "IL",
    "postal_code": "60630-2429",
    "phone": "(773) 286-6212",
    "email": "",
    "website": "",
    "entity_type": "",
    "business_started": "",
    "incorporated_date": "",
    "principal_contact": "",
    "business_categories": "Roofing Contractors; Sheet Metal Fabrication",
    "rating": "A+",
    "bbb_member": "true",
    "bbb_accredited": "true",
    "source_url": "https://www.bbb.org/us/il/chicago/profile/roofing-contractors/conrad-roofing-of-illinois-0654-86001632"
  },
  {
    "business_name": "Inishowen Roofing & Construction",
    "street_address": "4942 W Carmen Ave",
    "city": "Chicago",
    "state": "IL",
    "postal_code": "60630-2424",
    "phone": "(773) 962-7757",
    "email": "",
    "website": "",
    "entity_type": "",
    "business_started": "",
    "incorporated_date": "",
    "principal_contact": "",
    "business_categories": "Roofing Contractors; General Contractor; Painting Contractors; Siding Contractors",
    "rating": "A+",
    "bbb_member": "true",
    "bbb_accredited": "true",
    "source_url": "https://www.bbb.org/us/il/chicago/profile/roofing-contractors/inishowen-roofing-construction-0654-90019880"
  },
  {
    "business_name": "Conrad Roofing of Illinois",
    "street_address": "5122 N. Elston Ave.",
    "city": "Chicago",
    "state": "IL",
    "postal_code": "60630",
    "phone": "(773) 286-6212",
    "email": "",
    "website": "",
    "entity_type": "",
    "business_started": "",
    "incorporated_date": "",
    "principal_contact": "",
    "business_categories": "Roofing Contractors; Sheet Metal Fabrication",
    "rating": "A+",
    "bbb_member": "true",
    "bbb_accredited": "true",
    "source_url": "https://www.bbb.org/us/il/chicago/profile/roofing-contractors/conrad-roofing-of-illinois-0654-86001632"
  },
  {
    "business_name": "Midwest Roofing & Renovation",
    "street_address": "4057 N Narragansett Ave",
    "city": "Chicago",
    "state": "IL",
    "postal_code": "60634-1559",
    "phone": "(773) 851-2239",
    "email": "",
    "website": "",
    "entity_type": "",
    "business_started": "",
    "incorporated_date": "",
    "principal_contact": "",
    "business_categories": "Roofing Contractors; Siding Contractors; Gutters; Chimney Repair",
    "rating": "A+",
    "bbb_member": "true",
    "bbb_accredited": "true",
    "source_url": "https://www.bbb.org/us/il/chicago/profile/roofing-contractors/midwest-roofing-renovation-0654-1000030633"
  },
  {
    "business_name": "NEW AGE ROOFS, Inc",
    "street_address": "5743 W Lawrence Ave",
    "city": "Chicago",
    "state": "IL",
    "postal_code": "60630-3383",
    "phone": "(773) 698-1783",
    "email": "",
    "website": "",
    "entity_type": "",
    "business_started": "",
    "incorporated_date": "",
    "principal_contact": "",
    "business_categories": "Roofing Contractors; Siding Contractors; Metal Roofing Contractors; Commercial Roofing",
    "rating": "A+",
    "bbb_member": "true",
    "bbb_accredited": "false",
    "source_url": "https://www.bbb.org/us/il/chicago/profile/roofing-contractors/new-age-roofs-inc-0654-90031251"
  },
  {
    "business_name": "APR Roofing",
    "street_address": "6351 W Montrose Ave",
    "city": "Chicago",
    "state": "IL",
    "postal_code": "60634-1563",
    "phone": "(773) 930-9861",
    "email": "",
    "website": "",
    "entity_type": "",
    "business_started": "",
    "incorporated_date": "",
    "principal_contact": "",
    "business_categories": "Roofing Contractors; Metal Roofing Contractors; Commercial Roofing; Flat Roofing Contractors",
    "rating": "A+",
    "bbb_member": "true",
    "bbb_accredited": "false",
    "source_url": "https://www.bbb.org/us/il/chicago/profile/roofing-contractors/apr-roofing-0654-90004521"
  },
  {
    "business_name": "J & J Roofing & Construction",
    "street_address": "7249 W Archer Ave",
    "city": "Summit",
    "state": "IL",
    "postal_code": "60501-1255",
    "phone": "(708) 458-7988",
    "email": "",
    "website": "",
    "entity_type": "",
    "business_started": "",
    "incorporated_date": "",
    "principal_contact": "",
    "business_categories": "Roofing Contractors; Construction Services; Siding Contractors; Patios and Decks",
    "rating": "A+",
    "bbb_member": "true",
    "bbb_accredited": "true",
    "source_url": "https://www.bbb.org/us/il/summit/profile/roofing-contractors/j-j-roofing-construction-0654-34000577"
  },
  {
    "business_name": "Buk Roofing",
    "street_address": "3354 N Odell Ave",
    "city": "Chicago",
    "state": "IL",
    "postal_code": "60634-3437",
    "phone": "(773) 577-4019",
    "email": "",
    "website": "",
    "entity_type": "",
    "business_started": "",
    "incorporated_date": "",
    "principal_contact": "",
    "business_categories": "Roofing Contractors; Siding Contractors; Gutters; Chimney Repair",
    "rating": "A+",
    "bbb_member": "true",
    "bbb_accredited": "true",
    "source_url": "https://www.bbb.org/us/il/chicago/profile/roofing-contractors/buk-roofing-0654-88361603"
  },
  {
    "business_name": "Ameribuild & Roofing, Inc.",
    "street_address": "6124 W. Warwick",
    "city": "Chicago",
    "state": "IL",
    "postal_code": "60634-2556",
    "phone": "(773) 282-7700",
    "email": "",
    "website": "",
    "entity_type": "",
    "business_started": "",
    "incorporated_date": "",
    "principal_contact": "",
    "business_categories": "Roofing Contractors; Siding Contractors; Gutters; Water Damage Restoration",
    "rating": "A+",
    "bbb_member": "true",
    "bbb_accredited": "true",
    "source_url": "https://www.bbb.org/us/il/chicago/profile/roofing-contractors/ameribuild-roofing-inc-0654-88377630"
  },
  {
    "business_name": "T.A.R. Roofing Inc.",
    "street_address": "3400 N Natchez Ave",
    "city": "Chicago",
    "state": "IL",
    "postal_code": "60634-3817",
    "phone": "(630) 422-1589",
    "email": "",
    "website": "",
    "entity_type": "",
    "business_started": "",
    "incorporated_date": "",
    "principal_contact": "",
    "business_categories": "Roofing Contractors; Siding Contractors; Flat Roofing Contractors; Roof Leak Repair",
    "rating": "A+",
    "bbb_member": "true",
    "bbb_accredited": "true",
    "source_url": "https://www.bbb.org/us/il/chicago/profile/roofing-contractors/tar-roofing-inc-0654-88704530"
  },
  {
    "business_name": "Premier Roofing, Inc.",
    "street_address": "5568 N Lynch Ave",
    "city": "Chicago",
    "state": "IL",
    "postal_code": "60630-1453",
    "phone": "(773) 792-1446",
    "email": "",
    "website": "",
    "entity_type": "",
    "business_started": "",
    "incorporated_date": "",
    "principal_contact": "",
    "business_categories": "Roofing Contractors; Siding Contractors; Gutters",
    "rating": "A+",
    "bbb_member": "true",
    "bbb_accredited": "true",
    "source_url": "https://www.bbb.org/us/il/chicago/profile/roofing-contractors/premier-roofing-inc-0654-88388284"
  },
  {
    "business_name": "Eddie's Roofing & Exteriors Inc",
    "street_address": "7803 Lockwood Ave",
    "city": "Burbank",
    "state": "IL",
    "postal_code": "60459-1436",
    "phone": "(708) 774-5628",
    "email": "",
    "website": "",
    "entity_type": "",
    "business_started": "",
    "incorporated_date": "",
    "principal_contact": "",
    "business_categories": "Roofing Contractors; Siding Contractors; Gutters; Metal Roofing Contractors",
    "rating": "A+",
    "bbb_member": "true",
    "bbb_accredited": "true",
    "source_url": "https://www.bbb.org/us/il/burbank/profile/roofing-contractors/eddies-roofing-exteriors-inc-0654-1000037890"
  },
  {
    "business_name": "Perfect Roofing, Inc.",
    "street_address": "5115 N Mobile Ave",
    "city": "Jefferson Pk",
    "state": "IL",
    "postal_code": "60630-1838",
    "phone": "(773) 631-9120",
    "email": "",
    "website": "",
    "entity_type": "",
    "business_started": "",
    "incorporated_date": "",
    "principal_contact": "",
    "business_categories": "Roofing Contractors; Gutters; Soffit and Fascia",
    "rating": "A+",
    "bbb_member": "true",
    "bbb_accredited": "true",
    "source_url": "https://www.bbb.org/us/il/jefferson-pk/profile/roofing-contractors/perfect-roofing-inc-0654-73000255"
  },
  {
    "business_name": "Five Starz Construction & Roofing, Inc.",
    "street_address": "7701 Linder Ave",
    "city": "Burbank",
    "state": "IL",
    "postal_code": "60459",
    "phone": "(773) 392-2027",
    "email": "",
    "website": "",
    "entity_type": "",
    "business_started": "",
    "incorporated_date": "",
    "principal_contact": "",
    "business_categories": "Roofing Contractors; Siding Contractors; Gutters; Commercial Roofing",
    "rating": "A+",
    "bbb_member": "true",
    "bbb_accredited": "true",
    "source_url": "https://www.bbb.org/us/il/burbank/profile/roofing-contractors/five-starz-construction-roofing-inc-0654-88712087"
  },
  {
    "business_name": "Sandoval Roofing, LLC",
    "street_address": "129 S 16th Ave",
    "city": "Maywood",
    "state": "IL",
    "postal_code": "60153-1214",
    "phone": "(773) 954-7128",
    "email": "",
    "website": "",
    "entity_type": "",
    "business_started": "",
    "incorporated_date": "",
    "principal_contact": "",
    "business_categories": "Roofing Contractors; Commercial Roofing; Flat Roofing Contractors; Roof Inspection",
    "rating": "A+",
    "bbb_member": "true",
    "bbb_accredited": "false",
    "source_url": "https://www.bbb.org/us/il/maywood/profile/roofing-contractors/sandoval-roofing-llc-0654-90020553"
  },
  {
    "business_name": "Raincoat Roof Maintenance",
    "street_address": "2600 S 17th Ave",
    "city": "Broadview",
    "state": "IL",
    "postal_code": "60155-4721",
    "phone": "(708) 681-5757",
    "email": "",
    "website": "",
    "entity_type": "",
    "business_started": "",
    "incorporated_date": "",
    "principal_contact": "",
    "business_categories": "Commercial Roofing; Roofing Contractors; Metal Roofing Contractors; Flat Roofing Contractors",
    "rating": "A+",
    "bbb_member": "true",
    "bbb_accredited": "true",
    "source_url": "https://www.bbb.org/us/il/broadview/profile/commercial-roofing/raincoat-roof-maintenance-0654-12007833"
  },
  {
    "business_name": "Raincoat Roof Maintenance",
    "street_address": "1750 Parkes Drive",
    "city": "Broadview",
    "state": "IL",
    "postal_code": "60155",
    "phone": "(708) 681-5757",
    "email": "",
    "website": "",
    "entity_type": "",
    "business_started": "",
    "incorporated_date": "",
    "principal_contact": "",
    "business_categories": "Commercial Roofing; Roofing Contractors; Metal Roofing Contractors; Flat Roofing Contractors",
    "rating": "A+",
    "bbb_member": "true",
    "bbb_accredited": "true",
    "source_url": "https://www.bbb.org/us/il/broadview/profile/commercial-roofing/raincoat-roof-maintenance-0654-12007833"
  },
  {
    "business_name": "Lake Point Roofing, Inc.",
    "street_address": "9507 Ogden Ave",
    "city": "Brookfield",
    "state": "IL",
    "postal_code": "60513-1841",
    "phone": "(708) 485-8900",
    "email": "",
    "website": "",
    "entity_type": "",
    "business_started": "",
    "incorporated_date": "",
    "principal_contact": "",
    "business_categories": "Roofing Contractors; Gutters; Flat Roofing Contractors; Soffit and Fascia",
    "rating": "A+",
    "bbb_member": "true",
    "bbb_accredited": "true",
    "source_url": "https://www.bbb.org/us/il/brookfield/profile/roofing-contractors/lake-point-roofing-inc-0654-88386196"
  },
  {
    "business_name": "Licitra Roofing, Inc.",
    "street_address": "9512 W 47th St",
    "city": "Brookfield",
    "state": "IL",
    "postal_code": "60513-2289",
    "phone": "(708) 485-4848",
    "email": "",
    "website": "",
    "entity_type": "",
    "business_started": "",
    "incorporated_date": "",
    "principal_contact": "",
    "business_categories": "Roofing Contractors",
    "rating": "A+",
    "bbb_member": "true",
    "bbb_accredited": "true",
    "source_url": "https://www.bbb.org/us/il/brookfield/profile/roofing-contractors/licitra-roofing-inc-0654-28258"
  },
  {
    "business_name": "Care Sheet Metal & Roofing, Inc.",
    "street_address": "9536 47th St",
    "city": "Brookfield",
    "state": "IL",
    "postal_code": "60513-2251",
    "phone": "(708) 387-9784",
    "email": "",
    "website": "",
    "entity_type": "",
    "business_started": "",
    "incorporated_date": "",
    "principal_contact": "",
    "business_categories": "Roofing Contractors; Gutters; Spray Foam Insulation Contractors; Commercial Roofing",
    "rating": "A+",
    "bbb_member": "true",
    "bbb_accredited": "false",
    "source_url": "https://www.bbb.org/us/il/brookfield/profile/roofing-contractors/care-sheet-metal-roofing-inc-0654-7389"
  },
  {
    "business_name": "LifeTime Roofing",
    "street_address": "4348 N Oketo Ave",
    "city": "Norridge",
    "state": "IL",
    "postal_code": "60706-1133",
    "phone": "(773) 491-1290",
    "email": "",
    "website": "",
    "entity_type": "",
    "business_started": "",
    "incorporated_date": "",
    "principal_contact": "",
    "business_categories": "Commercial Roofing; Roofing Contractors; Metal Roofing Contractors; Flat Roofing Contractors",
    "rating": "A+",
    "bbb_member": "true",
    "bbb_accredited": "true",
    "source_url": "https://www.bbb.org/us/il/norridge/profile/commercial-roofing/lifetime-roofing-0654-90024074"
  },
  {
    "business_name": "Fellows Roofing, Ltd",
    "street_address": "P.O. Box 6371",
    "city": "Maywood",
    "state": "IL",
    "postal_code": "60155-6371",
    "phone": "(630) 629-9590",
    "email": "",
    "website": "",
    "entity_type": "",
    "business_started": "",
    "incorporated_date": "",
    "principal_contact": "",
    "business_categories": "Roofing Contractors; Siding Contractors; Gutter Contractors",
    "rating": "A+",
    "bbb_member": "true",
    "bbb_accredited": "true",
    "source_url": "https://www.bbb.org/us/il/la-grange-park/profile/roofing-contractors/fellows-roofing-ltd-0654-88435201"
  },
  {
    "business_name": "Becker Roofing Company",
    "street_address": "5692 N Milwaukee Ave",
    "city": "Chicago",
    "state": "IL",
    "postal_code": "60646-6222",
    "phone": "(773) 561-7344",
    "email": "",
    "website": "",
    "entity_type": "",
    "business_started": "",
    "incorporated_date": "",
    "principal_contact": "",
    "business_categories": "Roofing Contractors; Siding Contractors; Gutters; Chimney Repair",
    "rating": "A+",
    "bbb_member": "true",
    "bbb_accredited": "true",
    "source_url": "https://www.bbb.org/us/il/chicago/profile/roofing-contractors/becker-roofing-company-0654-4282"
  },
  {
    "business_name": "ACA Roofing & Construction, Inc.",
    "street_address": "3433 N Pontiac Ave # 1",
    "city": "Chicago",
    "state": "IL",
    "postal_code": "60634-2848",
    "phone": "(773) 936-3387",
    "email": "",
    "website": "",
    "entity_type": "",
    "business_started": "",
    "incorporated_date": "",
    "principal_contact": "",
    "business_categories": "Roofing Contractors; Siding Contractors; Windows; Window Installation",
    "rating": "A+",
    "bbb_member": "true",
    "bbb_accredited": "false",
    "source_url": "https://www.bbb.org/us/il/chicago/profile/roofing-contractors/aca-roofing-construction-inc-0654-49000878"
  },
  {
    "business_name": "Andres Roofing & Construction, Inc.",
    "street_address": "2736 W Touhy Avenue",
    "city": "Chicago",
    "state": "IL",
    "postal_code": "60645-3008",
    "phone": "(773) 508-1723",
    "email": "",
    "website": "",
    "entity_type": "",
    "business_started": "",
    "incorporated_date": "",
    "principal_contact": "",
    "business_categories": "Roofing Contractors; Siding Contractors; Gutters; Gutter Contractors",
    "rating": "A+",
    "bbb_member": "true",
    "bbb_accredited": "false",
    "source_url": "https://www.bbb.org/us/il/chicago/profile/roofing-contractors/andres-roofing-construction-inc-0654-88032119"
  },
  {
    "business_name": "CSR Roofing Contractors, Inc.",
    "street_address": "2540 S 27th Ave",
    "city": "Broadview",
    "state": "IL",
    "postal_code": "60155-3851",
    "phone": "(708) 848-9119",
    "email": "",
    "website": "",
    "entity_type": "",
    "business_started": "",
    "incorporated_date": "",
    "principal_contact": "",
    "business_categories": "Roofing Contractors; Siding Contractors; Gutters; Commercial Roofing",
    "rating": "A+",
    "bbb_member": "true",
    "bbb_accredited": "false",
    "source_url": "https://www.bbb.org/us/il/broadview/profile/roofing-contractors/csr-roofing-contractors-inc-0654-20295"
  },
  {
    "business_name": "F.E. Rooftec Corporation",
    "street_address": "9126 Medill Ave",
    "city": "Franklin Park",
    "state": "IL",
    "postal_code": "60131-3419",
    "phone": "(847) 455-4766",
    "email": "",
    "website": "",
    "entity_type": "",
    "business_started": "",
    "incorporated_date": "",
    "principal_contact": "",
    "business_categories": "Roofing Contractors; Siding Contractors; Patios and Decks; Gypsum",
    "rating": "A+",
    "bbb_member": "true",
    "bbb_accredited": "true",
    "source_url": "https://www.bbb.org/us/il/franklin-park/profile/roofing-contractors/fe-rooftec-corporation-0654-88194557"
  },
  {
    "business_name": "Aaron's Roofing & Masonry, Co.",
    "street_address": "8120 Mason Ave",
    "city": "Burbank",
    "state": "IL",
    "postal_code": "60459-1954",
    "phone": "(312) 927-7075",
    "email": "",
    "website": "",
    "entity_type": "",
    "business_started": "",
    "incorporated_date": "",
    "principal_contact": "",
    "business_categories": "Roofing Contractors; Chimney Repair; Deck Builder; Flat Roofing Contractors",
    "rating": "A+",
    "bbb_member": "true",
    "bbb_accredited": "true",
    "source_url": "https://www.bbb.org/us/il/burbank/profile/roofing-contractors/aarons-roofing-masonry-co-0654-1000023144"
  },
  {
    "business_name": "Fellows Roofing, Ltd",
    "street_address": "1009 Beach Ave",
    "city": "La Grange Park",
    "state": "IL",
    "postal_code": "60526-1677",
    "phone": "(630) 629-9590",
    "email": "",
    "website": "",
    "entity_type": "",
    "business_started": "",
    "incorporated_date": "",
    "principal_contact": "",
    "business_categories": "Roofing Contractors; Siding Contractors; Gutter Contractors",
    "rating": "A+",
    "bbb_member": "true",
    "bbb_accredited": "true",
    "source_url": "https://www.bbb.org/us/il/la-grange-park/profile/roofing-contractors/fellows-roofing-ltd-0654-88435201"
  },
  {
    "business_name": "Enrique Roofing Experts",
    "street_address": "4434 w Pratt ave",
    "city": "Lincolnwood",
    "state": "IL",
    "postal_code": "60712",
    "phone": "(773) 961-5023",
    "email": "",
    "website": "",
    "entity_type": "",
    "business_started": "",
    "incorporated_date": "",
    "principal_contact": "",
    "business_categories": "Roofing Contractors; Siding Contractors; Metal Roofing Contractors; Flat Roofing Contractors",
    "rating": "A+",
    "bbb_member": "true",
    "bbb_accredited": "true",
    "source_url": "https://www.bbb.org/us/il/lincolnwood/profile/roofing-contractors/enrique-roofing-experts-0654-1000043877"
  },
  {
    "business_name": "All Roofs, Inc.",
    "street_address": "9400 Schiller Blvd",
    "city": "Franklin Park",
    "state": "IL",
    "postal_code": "60131-2946",
    "phone": "(866) 205-8833",
    "email": "",
    "website": "",
    "entity_type": "",
    "business_started": "",
    "incorporated_date": "",
    "principal_contact": "",
    "business_categories": "Roofing Contractors; Concrete Contractors; Siding Contractors; Gutters",
    "rating": "A+",
    "bbb_member": "true",
    "bbb_accredited": "true",
    "source_url": "https://www.bbb.org/us/il/franklin-park/profile/roofing-contractors/all-roofs-inc-0654-13000297"
  },
  {
    "business_name": "PVP Roofing",
    "street_address": "7630 S Thomas Ave",
    "city": "Bridgeview",
    "state": "IL",
    "postal_code": "60455-1311",
    "phone": "(708) 458-6117",
    "email": "",
    "website": "",
    "entity_type": "",
    "business_started": "",
    "incorporated_date": "",
    "principal_contact": "",
    "business_categories": "Roofing Contractors; Siding Contractors; Gutters; Windows",
    "rating": "A+",
    "bbb_member": "true",
    "bbb_accredited": "true",
    "source_url": "https://www.bbb.org/us/il/bridgeview/profile/roofing-contractors/pvp-roofing-0654-1002420"
  },
  {
    "business_name": "Style Exteriors, Inc.",
    "street_address": "4905 W 95th St",
    "city": "Oak Lawn",
    "state": "IL",
    "postal_code": "60453-2503",
    "phone": "(847) 865-3069",
    "email": "",
    "website": "",
    "entity_type": "",
    "business_started": "",
    "incorporated_date": "",
    "principal_contact": "",
    "business_categories": "Construction Services; Roofing Contractors; Home Improvement; Siding Contractors",
    "rating": "A+",
    "bbb_member": "true",
    "bbb_accredited": "false",
    "source_url": "https://www.bbb.org/us/il/kildeer/profile/construction-services/style-exteriors-inc-0654-88378007"
  },
  {
    "business_name": "Style Exteriors by Corley",
    "street_address": "4905 95th Street",
    "city": "Oak Lawn",
    "state": "IL",
    "postal_code": "60453",
    "phone": "(708) 292-0410",
    "email": "",
    "website": "",
    "entity_type": "",
    "business_started": "",
    "incorporated_date": "",
    "principal_contact": "",
    "business_categories": "Roofing Contractors; Siding Contractors; Gutters; Windows",
    "rating": "A+",
    "bbb_member": "true",
    "bbb_accredited": "true",
    "source_url": "https://www.bbb.org/us/il/oak-lawn/profile/roofing-contractors/style-exteriors-by-corley-0654-90025216"
  },
  {
    "business_name": "Iron Guys Roofing and Restoration LLC",
    "street_address": "10526 W Cermak Rd",
    "city": "Westchester",
    "state": "IL",
    "postal_code": "60154-5249",
    "phone": "(708) 506-2641",
    "email": "",
    "website": "",
    "entity_type": "",
    "business_started": "",
    "incorporated_date": "",
    "principal_contact": "",
    "business_categories": "Roofing Contractors; General Contractor; Siding Contractors; Gutters",
    "rating": "A+",
    "bbb_member": "true",
    "bbb_accredited": "true",
    "source_url": "https://www.bbb.org/us/il/westchester/profile/roofing-contractors/iron-guys-roofing-and-restoration-llc-0654-90027994"
  },
  {
    "business_name": "Green Attic Roofing",
    "street_address": "3940 Willow St",
    "city": "Schiller Park",
    "state": "IL",
    "postal_code": "60176-2311",
    "phone": "(847) 871-9999",
    "email": "",
    "website": "",
    "entity_type": "",
    "business_started": "",
    "incorporated_date": "",
    "principal_contact": "",
    "business_categories": "Roofing Contractors; Metal Roofing Contractors; Commercial Roofing; Flat Roofing Contractors",
    "rating": "A ",
    "bbb_member": "true",
    "bbb_accredited": "true",
    "source_url": "https://www.bbb.org/us/il/schiller-park/profile/roofing-contractors/green-attic-roofing-0654-1000106616"
  },
  {
    "business_name": "New Generation Exteriors Corp",
    "street_address": "8521 S 77th Ct",
    "city": "Bridgeview",
    "state": "IL",
    "postal_code": "60455-1746",
    "phone": "(630) 256-0369",
    "email": "",
    "website": "",
    "entity_type": "",
    "business_started": "",
    "incorporated_date": "",
    "principal_contact": "",
    "business_categories": "Roofing Contractors; Siding Contractors; Gutters; Commercial Roofing",
    "rating": "A+",
    "bbb_member": "true",
    "bbb_accredited": "true",
    "source_url": "https://www.bbb.org/us/il/bridgeview/profile/roofing-contractors/new-generation-exteriors-corp-0654-90009696"
  },
  {
    "business_name": "AGG Roofing",
    "street_address": "7931 Kedvale Ave",
    "city": "Skokie",
    "state": "IL",
    "postal_code": "60076",
    "phone": "(847) 972-1893",
    "email": "",
    "website": "",
    "entity_type": "",
    "business_started": "",
    "incorporated_date": "",
    "principal_contact": "",
    "business_categories": "Roofing Contractors; Metal Roofing Contractors; Commercial Roofing; Flat Roofing Contractors",
    "rating": "A+",
    "bbb_member": "true",
    "bbb_accredited": "false",
    "source_url": "https://www.bbb.org/us/il/skokie/profile/roofing-contractors/agg-roofing-0654-88652641"
  },
  {
    "business_name": "MLS Construction & Roofing, Inc.",
    "street_address": "10101 S Homan Ave",
    "city": "Evergreen Park",
    "state": "IL",
    "postal_code": "60805-3723",
    "phone": "(773) 569-7487",
    "email": "",
    "website": "",
    "entity_type": "",
    "business_started": "",
    "incorporated_date": "",
    "principal_contact": "",
    "business_categories": "General Contractor; Roofing Contractors; Construction Services; Concrete Contractors",
    "rating": "A+",
    "bbb_member": "true",
    "bbb_accredited": "true",
    "source_url": "https://www.bbb.org/us/il/alsip/profile/general-contractor/mls-construction-roofing-inc-0654-88600129"
  },
  {
    "business_name": "GTG Services Chicago Siding and Roofing",
    "street_address": "9405 Seymour Ave",
    "city": "Schiller Park",
    "state": "IL",
    "postal_code": "60176-2123",
    "phone": "(773) 308-3901",
    "email": "",
    "website": "",
    "entity_type": "",
    "business_started": "",
    "incorporated_date": "",
    "principal_contact": "",
    "business_categories": "Roofing Contractors; Siding Contractors; Gutters; Metal Roofing Contractors",
    "rating": "A+",
    "bbb_member": "true",
    "bbb_accredited": "true",
    "source_url": "https://www.bbb.org/us/il/schiller-park/profile/roofing-contractors/gtg-services-chicago-siding-and-roofing-0654-90003175"
  },
  {
    "business_name": "O'Hara's Son Roofing Company",
    "street_address": "6437 N Avondale Ave",
    "city": "Chicago",
    "state": "IL",
    "postal_code": "60631-1909",
    "phone": "(847) 255-3600",
    "email": "",
    "website": "",
    "entity_type": "",
    "business_started": "",
    "incorporated_date": "",
    "principal_contact": "",
    "business_categories": "Roofing Contractors; Construction Services; Gutters; Gutter Cleaning",
    "rating": "A+",
    "bbb_member": "true",
    "bbb_accredited": "true",
    "source_url": "https://www.bbb.org/us/il/chicago/profile/roofing-contractors/oharas-son-roofing-company-0654-12014651"
  },
  {
    "business_name": "Summit Roofing Corp.",
    "street_address": "2942 Becket Ave",
    "city": "Westchester",
    "state": "IL",
    "postal_code": "60154-5619",
    "phone": "(773) 655-8529",
    "email": "",
    "website": "",
    "entity_type": "",
    "business_started": "",
    "incorporated_date": "",
    "principal_contact": "",
    "business_categories": "Roofing Contractors; Siding Contractors; Windows; Metal Roofing Contractors",
    "rating": "A+",
    "bbb_member": "true",
    "bbb_accredited": "false",
    "source_url": "https://www.bbb.org/us/il/westchester/profile/roofing-contractors/summit-roofing-corp-0654-88696928"
  },
  {
    "business_name": "Style Exteriors by Corley",
    "street_address": "10600 S Cicero Ave",
    "city": "Oak Lawn",
    "state": "IL",
    "postal_code": "60453-5911",
    "phone": "(708) 292-0410",
    "email": "",
    "website": "",
    "entity_type": "",
    "business_started": "",
    "incorporated_date": "",
    "principal_contact": "",
    "business_categories": "Roofing Contractors; Siding Contractors; Gutters; Windows",
    "rating": "A+",
    "bbb_member": "true",
    "bbb_accredited": "true",
    "source_url": "https://www.bbb.org/us/il/oak-lawn/profile/roofing-contractors/style-exteriors-by-corley-0654-90025216"
  },
  {
    "business_name": "BNF Roofing PROS, LLC",
    "street_address": "3409 Hawthorne St",
    "city": "Franklin Park",
    "state": "IL",
    "postal_code": "60131-1715",
    "phone": "(312) 889-8853",
    "email": "",
    "website": "",
    "entity_type": "",
    "business_started": "",
    "incorporated_date": "",
    "principal_contact": "",
    "business_categories": "Roofing Contractors; Siding Contractors; Business Consultants; Soffit and Fascia",
    "rating": "A+",
    "bbb_member": "true",
    "bbb_accredited": "true",
    "source_url": "https://www.bbb.org/us/il/franklin-park/profile/roofing-contractors/bnf-roofing-pros-llc-0654-90029932"
  },
  {
    "business_name": "Prusak Roofing, Inc.",
    "street_address": "8907 Odell Ave",
    "city": "Bridgeview",
    "state": "IL",
    "postal_code": "60455-1913",
    "phone": "(708) 422-2624",
    "email": "",
    "website": "",
    "entity_type": "",
    "business_started": "",
    "incorporated_date": "",
    "principal_contact": "",
    "business_categories": "Roofing Contractors; Siding Contractors; Gutters; Metal Roofing Contractors",
    "rating": "A+",
    "bbb_member": "true",
    "bbb_accredited": "true",
    "source_url": "https://www.bbb.org/us/il/bridgeview/profile/roofing-contractors/prusak-roofing-inc-0654-51000487"
  }
]